<?xml version="1.0" encoding="ISO-8859-1"?>
<!DOCTYPE POWERMART SYSTEM "powrmart.dtd">
<POWERMART CREATION_DATE="04/20/2025 10:30:00" REPOSITORY_VERSION="187.96">
  <REPOSITORY NAME="SampleRepo" VERSION="187" CODEPAGE="Latin1" DATABASETYPE="Oracle">
    <FOLDER NAME="SampleFolder" OWNER="Administrator" SHARED="NOTSHARED">
      <!-- Source Definition -->
      <SOURCE NAME="EMPLOYEE_SOURCE" DATABASETYPE="Oracle">
        <SOURCEFIELD NAME="EMP_ID" DATATYPE="number" PRECISION="10" SCALE="0"/>
        <SOURCEFIELD NAME="EMP_NAME" DATATYPE="varchar2" PRECISION="50" SCALE="0"/>
      </SOURCE>

      <!-- Target Definition -->
      <TARGET NAME="EMPLOYEE_TARGET" DATABASETYPE="Oracle">
        <TARGETFIELD NAME="EMP_ID" DATATYPE="number" PRECISION="10" SCALE="0"/>
        <TARGETFIELD NAME="EMP_NAME" DATATYPE="varchar2" PRECISION="50" SCALE="0"/>
      </TARGET>

      <!-- Mapping -->
      <MAPPING NAME="m_LOAD_EMPLOYEE">
        <!-- Source Qualifier Transformation -->
        <TRANSFORMATION NAME="SQ_EMPLOYEE" TYPE="Source Qualifier">
          <TRANSFORMFIELD NAME="EMP_ID" PORTTYPE="INPUT/OUTPUT" DATATYPE="number" PRECISION="10" SCALE="0"/>
          <TRANSFORMFIELD NAME="EMP_NAME" PORTTYPE="INPUT/OUTPUT" DATATYPE="varchar2" PRECISION="50" SCALE="0"/>
        </TRANSFORMATION>

        <!-- Expression Transformation -->
        <TRANSFORMATION NAME="EXP_EMPLOYEE" TYPE="Expression">
          <TRANSFORMFIELD NAME="EMP_ID" PORTTYPE="INPUT/OUTPUT" DATATYPE="number" PRECISION="10" SCALE="0"/>
          <TRANSFORMFIELD NAME="EMP_NAME" PORTTYPE="INPUT/OUTPUT" DATATYPE="varchar2" PRECISION="50" SCALE="0"/>
        </TRANSFORMATION>

        <!-- Instances -->
        <INSTANCE NAME="EMPLOYEE_SOURCE" TRANSFORMATION_NAME="EMPLOYEE_SOURCE" TRANSFORMATION_TYPE="Source Definition" TYPE="SOURCE"/>
        <INSTANCE NAME="EMPLOYEE_TARGET" TRANSFORMATION_NAME="EMPLOYEE_TARGET" TRANSFORMATION_TYPE="Target Definition" TYPE="TARGET"/>
        <INSTANCE NAME="SQ_EMPLOYEE" TRANSFORMATION_NAME="SQ_EMPLOYEE" TRANSFORMATION_TYPE="Source Qualifier" TYPE="TRANSFORMATION">
          <ASSOCIATED_SOURCE_INSTANCE NAME="EMPLOYEE_SOURCE"/>
        </INSTANCE>
        <INSTANCE NAME="EXP_EMPLOYEE" TRANSFORMATION_NAME="EXP_EMPLOYEE" TRANSFORMATION_TYPE="Expression" TYPE="TRANSFORMATION"/>

        <!-- Connectors -->
        <CONNECTOR FROMFIELD="EMP_ID" FROMINSTANCE="EMPLOYEE_SOURCE" TOFIELD="EMP_ID" TOINSTANCE="SQ_EMPLOYEE"/>
        <CONNECTOR FROMFIELD="EMP_NAME" FROMINSTANCE="EMPLOYEE_SOURCE" TOFIELD="EMP_NAME" TOINSTANCE="SQ_EMPLOYEE"/>

        <CONNECTOR FROMFIELD="EMP_ID" FROMINSTANCE="SQ_EMPLOYEE" TOFIELD="EMP_ID" TOINSTANCE="EXP_EMPLOYEE"/>
        <CONNECTOR FROMFIELD="EMP_NAME" FROMINSTANCE="SQ_EMPLOYEE" TOFIELD="EMP_NAME" TOINSTANCE="EXP_EMPLOYEE"/>

        <CONNECTOR FROMFIELD="EMP_ID" FROMINSTANCE="EXP_EMPLOYEE" TOFIELD="EMP_ID" TOINSTANCE="EMPLOYEE_TARGET"/>
        <CONNECTOR FROMFIELD="EMP_NAME" FROMINSTANCE="EXP_EMPLOYEE" TOFIELD="EMP_NAME" TOINSTANCE="EMPLOYEE_TARGET"/>

      </MAPPING>
    </FOLDER>
  </REPOSITORY>
</POWERMART>
